{"is_source_file": false, "format": "", "description": "", "external_files": [], "external_methods": [], "published": [], "classes": [], "methods": [], "calls": [], "search-terms": [], "state": 2, "file_id": 1, "knowledge_revision": 20, "git_revision": "0e7af0e9a5d816b43febfba2e1ccaad0f4ac5085", "hash": "9b7236b1e4c5102923b86971da5a8096", "format-version": 4, "code-base-name": "vod_android_tv_frontend", "filename": "README.md", "revision_history": [{"20": "0e7af0e9a5d816b43febfba2e1ccaad0f4ac5085"}]}